{"name":"YamlConfigurationOptions","comment":"Various settings for controlling the input and output of a {@link\n YamlConfiguration}","isClass":true,"isInterface":false,"isEnum":false,"isEnumConstant":false,"isConstructor":false,"isField":false,"isMethod":false,"isOrdinaryClass":true,"isPrimitive":false,"simpleName":"YamlConfigurationOptions","qualifiedName":"org.bukkit.configuration.file.YamlConfigurationOptions","dimension":"","elementType":{},"package":"org.bukkit.configuration.file","superclass":"org.bukkit.configuration.file.FileConfigurationOptions","interfaces":[],"isAbstract":false,"isStatic":false,"innerClasses":[],"isInnerClass":false,"constructors":[],"fields":[],"methods":[{"name":"configuration","comment":"","isClass":false,"isInterface":false,"isEnum":false,"isEnumConstant":false,"isConstructor":false,"isField":false,"isMethod":true,"isOrdinaryClass":false,"signature":"()","flatSignature":"()","returnType":{"isPrimitive":false,"simpleName":"YamlConfiguration","qualifiedName":"org.bukkit.configuration.file.YamlConfiguration","dimension":"","elementType":{}},"isAbstract":false,"isDefault":false,"isStatic":false,"parameters":[],"typeParameters":[]},{"name":"copyDefaults","comment":"","isClass":false,"isInterface":false,"isEnum":false,"isEnumConstant":false,"isConstructor":false,"isField":false,"isMethod":true,"isOrdinaryClass":false,"signature":"(boolean)","flatSignature":"(boolean)","returnType":{"isPrimitive":false,"simpleName":"YamlConfigurationOptions","qualifiedName":"org.bukkit.configuration.file.YamlConfigurationOptions","dimension":"","elementType":{}},"isAbstract":false,"isDefault":false,"isStatic":false,"parameters":[{"name":"value","type":{"isPrimitive":true,"simpleName":"boolean","qualifiedName":"boolean","dimension":"","elementType":{}}}],"typeParameters":[]},{"name":"pathSeparator","comment":"","isClass":false,"isInterface":false,"isEnum":false,"isEnumConstant":false,"isConstructor":false,"isField":false,"isMethod":true,"isOrdinaryClass":false,"signature":"(char)","flatSignature":"(char)","returnType":{"isPrimitive":false,"simpleName":"YamlConfigurationOptions","qualifiedName":"org.bukkit.configuration.file.YamlConfigurationOptions","dimension":"","elementType":{}},"isAbstract":false,"isDefault":false,"isStatic":false,"parameters":[{"name":"value","type":{"isPrimitive":true,"simpleName":"char","qualifiedName":"char","dimension":"","elementType":{}}}],"typeParameters":[]},{"name":"header","comment":"","isClass":false,"isInterface":false,"isEnum":false,"isEnumConstant":false,"isConstructor":false,"isField":false,"isMethod":true,"isOrdinaryClass":false,"signature":"(java.lang.String)","flatSignature":"(String)","returnType":{"isPrimitive":false,"simpleName":"YamlConfigurationOptions","qualifiedName":"org.bukkit.configuration.file.YamlConfigurationOptions","dimension":"","elementType":{}},"isAbstract":false,"isDefault":false,"isStatic":false,"parameters":[{"name":"value","type":{"isPrimitive":false,"simpleName":"String","qualifiedName":"java.lang.String","dimension":"","elementType":{}}}],"typeParameters":[]},{"name":"copyHeader","comment":"","isClass":false,"isInterface":false,"isEnum":false,"isEnumConstant":false,"isConstructor":false,"isField":false,"isMethod":true,"isOrdinaryClass":false,"signature":"(boolean)","flatSignature":"(boolean)","returnType":{"isPrimitive":false,"simpleName":"YamlConfigurationOptions","qualifiedName":"org.bukkit.configuration.file.YamlConfigurationOptions","dimension":"","elementType":{}},"isAbstract":false,"isDefault":false,"isStatic":false,"parameters":[{"name":"value","type":{"isPrimitive":true,"simpleName":"boolean","qualifiedName":"boolean","dimension":"","elementType":{}}}],"typeParameters":[]},{"name":"indent","comment":"Gets how much spaces should be used to indent each line.\n \u003cp\u003e\n The minimum value this may be is 2, and the maximum is 9.","isClass":false,"isInterface":false,"isEnum":false,"isEnumConstant":false,"isConstructor":false,"isField":false,"isMethod":true,"isOrdinaryClass":false,"signature":"()","flatSignature":"()","returnType":{"isPrimitive":true,"simpleName":"int","qualifiedName":"int","dimension":"","elementType":{}},"isAbstract":false,"isDefault":false,"isStatic":false,"parameters":[],"typeParameters":[]},{"name":"indent","comment":"Sets how much spaces should be used to indent each line.\n \u003cp\u003e\n The minimum value this may be is 2, and the maximum is 9.","isClass":false,"isInterface":false,"isEnum":false,"isEnumConstant":false,"isConstructor":false,"isField":false,"isMethod":true,"isOrdinaryClass":false,"signature":"(int)","flatSignature":"(int)","returnType":{"isPrimitive":false,"simpleName":"YamlConfigurationOptions","qualifiedName":"org.bukkit.configuration.file.YamlConfigurationOptions","dimension":"","elementType":{}},"isAbstract":false,"isDefault":false,"isStatic":false,"parameters":[{"name":"value","type":{"isPrimitive":true,"simpleName":"int","qualifiedName":"int","dimension":"","elementType":{}}}],"typeParameters":[]}],"typeParameters":[],"enumConstants":[]}