{"name":"PluginLoader","isClass":false,"isInterface":true,"isEnum":false,"isEnumConstant":false,"isConstructor":false,"isField":false,"isMethod":false,"isOrdinaryClass":false,"isPrimitive":false,"simpleName":"PluginLoader","qualifiedName":"org.bukkit.plugin.PluginLoader","dimension":"","elementType":{},"package":"org.bukkit.plugin","interfaces":[],"isAbstract":true,"isStatic":false,"innerClasses":[],"isInnerClass":false,"constructors":[],"fields":[],"methods":[{"name":"loadPlugin","isClass":false,"isInterface":false,"isEnum":false,"isEnumConstant":false,"isConstructor":false,"isField":false,"isMethod":true,"isOrdinaryClass":false,"signature":"(java.io.File)","flatSignature":"(File)","returnType":{"isPrimitive":false,"simpleName":"Plugin","qualifiedName":"org.bukkit.plugin.Plugin","dimension":"","elementType":{}},"isAbstract":true,"isDefault":false,"isStatic":false,"parameters":[{"name":"file","type":{"isPrimitive":false,"simpleName":"File","qualifiedName":"java.io.File","dimension":"","elementType":{}}}],"typeParameters":[]},{"name":"getPluginDescription","isClass":false,"isInterface":false,"isEnum":false,"isEnumConstant":false,"isConstructor":false,"isField":false,"isMethod":true,"isOrdinaryClass":false,"signature":"(java.io.File)","flatSignature":"(File)","returnType":{"isPrimitive":false,"simpleName":"PluginDescriptionFile","qualifiedName":"org.bukkit.plugin.PluginDescriptionFile","dimension":"","elementType":{}},"isAbstract":true,"isDefault":false,"isStatic":false,"parameters":[{"name":"file","type":{"isPrimitive":false,"simpleName":"File","qualifiedName":"java.io.File","dimension":"","elementType":{}}}],"typeParameters":[]},{"name":"getPluginFileFilters","isClass":false,"isInterface":false,"isEnum":false,"isEnumConstant":false,"isConstructor":false,"isField":false,"isMethod":true,"isOrdinaryClass":false,"signature":"()","flatSignature":"()","returnType":{"isPrimitive":false,"simpleName":"Pattern","qualifiedName":"java.util.regex.Pattern","dimension":"[]","elementType":{"isPrimitive":false,"simpleName":"Pattern","qualifiedName":"java.util.regex.Pattern","dimension":"","elementType":{}}},"isAbstract":true,"isDefault":false,"isStatic":false,"parameters":[],"typeParameters":[]},{"name":"createRegisteredListeners","isClass":false,"isInterface":false,"isEnum":false,"isEnumConstant":false,"isConstructor":false,"isField":false,"isMethod":true,"isOrdinaryClass":false,"signature":"(org.bukkit.event.Listener, org.bukkit.plugin.Plugin)","flatSignature":"(Listener, Plugin)","returnType":{"isPrimitive":false,"simpleName":"Map","qualifiedName":"java.util.Map","dimension":"","elementType":{}},"isAbstract":true,"isDefault":false,"isStatic":false,"parameters":[{"name":"listener","type":{"isPrimitive":false,"simpleName":"Listener","qualifiedName":"org.bukkit.event.Listener","dimension":"","elementType":{}}},{"name":"plugin","type":{"isPrimitive":false,"simpleName":"Plugin","qualifiedName":"org.bukkit.plugin.Plugin","dimension":"","elementType":{}}}],"typeParameters":[]},{"name":"enablePlugin","isClass":false,"isInterface":false,"isEnum":false,"isEnumConstant":false,"isConstructor":false,"isField":false,"isMethod":true,"isOrdinaryClass":false,"signature":"(org.bukkit.plugin.Plugin)","flatSignature":"(Plugin)","returnType":{"isPrimitive":true,"simpleName":"void","qualifiedName":"void","dimension":"","elementType":{}},"isAbstract":true,"isDefault":false,"isStatic":false,"parameters":[{"name":"plugin","type":{"isPrimitive":false,"simpleName":"Plugin","qualifiedName":"org.bukkit.plugin.Plugin","dimension":"","elementType":{}}}],"typeParameters":[]},{"name":"disablePlugin","isClass":false,"isInterface":false,"isEnum":false,"isEnumConstant":false,"isConstructor":false,"isField":false,"isMethod":true,"isOrdinaryClass":false,"signature":"(org.bukkit.plugin.Plugin)","flatSignature":"(Plugin)","returnType":{"isPrimitive":true,"simpleName":"void","qualifiedName":"void","dimension":"","elementType":{}},"isAbstract":true,"isDefault":false,"isStatic":false,"parameters":[{"name":"plugin","type":{"isPrimitive":false,"simpleName":"Plugin","qualifiedName":"org.bukkit.plugin.Plugin","dimension":"","elementType":{}}}],"typeParameters":[]}],"typeParameters":[],"enumConstants":[]}