{"name":"PlayerInventory","comment":"Interface to the inventory of a Player, including the four armor slots and any extra slots.","isClass":false,"isInterface":true,"isEnum":false,"isEnumConstant":false,"isConstructor":false,"isField":false,"isMethod":false,"isOrdinaryClass":false,"isPrimitive":false,"simpleName":"PlayerInventory","qualifiedName":"org.bukkit.inventory.PlayerInventory","dimension":"","elementType":{},"package":"org.bukkit.inventory","interfaces":["org.bukkit.inventory.Inventory"],"isAbstract":true,"isStatic":false,"innerClasses":[],"isInnerClass":false,"constructors":[],"fields":[],"methods":[{"name":"getArmorContents","comment":"Get all ItemStacks from the armor slots","isClass":false,"isInterface":false,"isEnum":false,"isEnumConstant":false,"isConstructor":false,"isField":false,"isMethod":true,"isOrdinaryClass":false,"signature":"()","flatSignature":"()","returnType":{"isPrimitive":false,"simpleName":"ItemStack","qualifiedName":"org.bukkit.inventory.ItemStack","dimension":"[]","elementType":{"isPrimitive":false,"simpleName":"ItemStack","qualifiedName":"org.bukkit.inventory.ItemStack","dimension":"","elementType":{}}},"isAbstract":true,"isDefault":false,"isStatic":false,"parameters":[],"typeParameters":[]},{"name":"getExtraContents","comment":"Get all additional ItemStacks stored in this inventory.\n \u003cbr\u003e\n NB: What defines an extra slot is up to the implementation, however it\n will not be contained within {@link #getStorageContents()} or\n {@link #getArmorContents()}","isClass":false,"isInterface":false,"isEnum":false,"isEnumConstant":false,"isConstructor":false,"isField":false,"isMethod":true,"isOrdinaryClass":false,"signature":"()","flatSignature":"()","returnType":{"isPrimitive":false,"simpleName":"ItemStack","qualifiedName":"org.bukkit.inventory.ItemStack","dimension":"[]","elementType":{"isPrimitive":false,"simpleName":"ItemStack","qualifiedName":"org.bukkit.inventory.ItemStack","dimension":"","elementType":{}}},"isAbstract":true,"isDefault":false,"isStatic":false,"parameters":[],"typeParameters":[]},{"name":"getHelmet","comment":"Return the ItemStack from the helmet slot","isClass":false,"isInterface":false,"isEnum":false,"isEnumConstant":false,"isConstructor":false,"isField":false,"isMethod":true,"isOrdinaryClass":false,"signature":"()","flatSignature":"()","returnType":{"isPrimitive":false,"simpleName":"ItemStack","qualifiedName":"org.bukkit.inventory.ItemStack","dimension":"","elementType":{}},"isAbstract":true,"isDefault":false,"isStatic":false,"parameters":[],"typeParameters":[]},{"name":"getChestplate","comment":"Return the ItemStack from the chestplate slot","isClass":false,"isInterface":false,"isEnum":false,"isEnumConstant":false,"isConstructor":false,"isField":false,"isMethod":true,"isOrdinaryClass":false,"signature":"()","flatSignature":"()","returnType":{"isPrimitive":false,"simpleName":"ItemStack","qualifiedName":"org.bukkit.inventory.ItemStack","dimension":"","elementType":{}},"isAbstract":true,"isDefault":false,"isStatic":false,"parameters":[],"typeParameters":[]},{"name":"getLeggings","comment":"Return the ItemStack from the leg slot","isClass":false,"isInterface":false,"isEnum":false,"isEnumConstant":false,"isConstructor":false,"isField":false,"isMethod":true,"isOrdinaryClass":false,"signature":"()","flatSignature":"()","returnType":{"isPrimitive":false,"simpleName":"ItemStack","qualifiedName":"org.bukkit.inventory.ItemStack","dimension":"","elementType":{}},"isAbstract":true,"isDefault":false,"isStatic":false,"parameters":[],"typeParameters":[]},{"name":"getBoots","comment":"Return the ItemStack from the boots slot","isClass":false,"isInterface":false,"isEnum":false,"isEnumConstant":false,"isConstructor":false,"isField":false,"isMethod":true,"isOrdinaryClass":false,"signature":"()","flatSignature":"()","returnType":{"isPrimitive":false,"simpleName":"ItemStack","qualifiedName":"org.bukkit.inventory.ItemStack","dimension":"","elementType":{}},"isAbstract":true,"isDefault":false,"isStatic":false,"parameters":[],"typeParameters":[]},{"name":"setItem","comment":"Stores the ItemStack at the given index of the inventory.\n \u003cp\u003e\n Indexes 0 through 8 refer to the hotbar. 9 through 35 refer to the main inventory, counting up from 9 at the top\n left corner of the inventory, moving to the right, and moving to the row below it back on the left side when it\n reaches the end of the row. It follows the same path in the inventory like you would read a book.\n \u003cp\u003e\n Indexes 36 through 39 refer to the armor slots. Though you can set armor with this method using these indexes,\n you are encouraged to use the provided methods for those slots.\n \u003cp\u003e\n Index 40 refers to the off hand (shield) item slot. Though you can set off hand with this method using this index,\n you are encouraged to use the provided method for this slot.\n \u003cp\u003e\n If you attempt to use this method with an index less than 0 or greater than 40, an ArrayIndexOutOfBounds\n exception will be thrown.","isClass":false,"isInterface":false,"isEnum":false,"isEnumConstant":false,"isConstructor":false,"isField":false,"isMethod":true,"isOrdinaryClass":false,"signature":"(int, org.bukkit.inventory.ItemStack)","flatSignature":"(int, ItemStack)","returnType":{"isPrimitive":true,"simpleName":"void","qualifiedName":"void","dimension":"","elementType":{}},"isAbstract":true,"isDefault":false,"isStatic":false,"parameters":[{"name":"index","type":{"isPrimitive":true,"simpleName":"int","qualifiedName":"int","dimension":"","elementType":{}}},{"name":"item","type":{"isPrimitive":false,"simpleName":"ItemStack","qualifiedName":"org.bukkit.inventory.ItemStack","dimension":"","elementType":{}}}],"typeParameters":[]},{"name":"setArmorContents","comment":"Put the given ItemStacks into the armor slots","isClass":false,"isInterface":false,"isEnum":false,"isEnumConstant":false,"isConstructor":false,"isField":false,"isMethod":true,"isOrdinaryClass":false,"signature":"(org.bukkit.inventory.ItemStack[])","flatSignature":"(ItemStack[])","returnType":{"isPrimitive":true,"simpleName":"void","qualifiedName":"void","dimension":"","elementType":{}},"isAbstract":true,"isDefault":false,"isStatic":false,"parameters":[{"name":"items","type":{"isPrimitive":false,"simpleName":"ItemStack","qualifiedName":"org.bukkit.inventory.ItemStack","dimension":"[]","elementType":{"isPrimitive":false,"simpleName":"ItemStack","qualifiedName":"org.bukkit.inventory.ItemStack","dimension":"","elementType":{}}}}],"typeParameters":[]},{"name":"setExtraContents","comment":"Put the given ItemStacks into the extra slots\n \u003cbr\u003e\n See {@link #getExtraContents()} for an explanation of extra slots.","isClass":false,"isInterface":false,"isEnum":false,"isEnumConstant":false,"isConstructor":false,"isField":false,"isMethod":true,"isOrdinaryClass":false,"signature":"(org.bukkit.inventory.ItemStack[])","flatSignature":"(ItemStack[])","returnType":{"isPrimitive":true,"simpleName":"void","qualifiedName":"void","dimension":"","elementType":{}},"isAbstract":true,"isDefault":false,"isStatic":false,"parameters":[{"name":"items","type":{"isPrimitive":false,"simpleName":"ItemStack","qualifiedName":"org.bukkit.inventory.ItemStack","dimension":"[]","elementType":{"isPrimitive":false,"simpleName":"ItemStack","qualifiedName":"org.bukkit.inventory.ItemStack","dimension":"","elementType":{}}}}],"typeParameters":[]},{"name":"setHelmet","comment":"Put the given ItemStack into the helmet slot. This does not check if\n the ItemStack is a helmet","isClass":false,"isInterface":false,"isEnum":false,"isEnumConstant":false,"isConstructor":false,"isField":false,"isMethod":true,"isOrdinaryClass":false,"signature":"(org.bukkit.inventory.ItemStack)","flatSignature":"(ItemStack)","returnType":{"isPrimitive":true,"simpleName":"void","qualifiedName":"void","dimension":"","elementType":{}},"isAbstract":true,"isDefault":false,"isStatic":false,"parameters":[{"name":"helmet","type":{"isPrimitive":false,"simpleName":"ItemStack","qualifiedName":"org.bukkit.inventory.ItemStack","dimension":"","elementType":{}}}],"typeParameters":[]},{"name":"setChestplate","comment":"Put the given ItemStack into the chestplate slot. This does not check\n if the ItemStack is a chestplate","isClass":false,"isInterface":false,"isEnum":false,"isEnumConstant":false,"isConstructor":false,"isField":false,"isMethod":true,"isOrdinaryClass":false,"signature":"(org.bukkit.inventory.ItemStack)","flatSignature":"(ItemStack)","returnType":{"isPrimitive":true,"simpleName":"void","qualifiedName":"void","dimension":"","elementType":{}},"isAbstract":true,"isDefault":false,"isStatic":false,"parameters":[{"name":"chestplate","type":{"isPrimitive":false,"simpleName":"ItemStack","qualifiedName":"org.bukkit.inventory.ItemStack","dimension":"","elementType":{}}}],"typeParameters":[]},{"name":"setLeggings","comment":"Put the given ItemStack into the leg slot. This does not check if the\n ItemStack is a pair of leggings","isClass":false,"isInterface":false,"isEnum":false,"isEnumConstant":false,"isConstructor":false,"isField":false,"isMethod":true,"isOrdinaryClass":false,"signature":"(org.bukkit.inventory.ItemStack)","flatSignature":"(ItemStack)","returnType":{"isPrimitive":true,"simpleName":"void","qualifiedName":"void","dimension":"","elementType":{}},"isAbstract":true,"isDefault":false,"isStatic":false,"parameters":[{"name":"leggings","type":{"isPrimitive":false,"simpleName":"ItemStack","qualifiedName":"org.bukkit.inventory.ItemStack","dimension":"","elementType":{}}}],"typeParameters":[]},{"name":"setBoots","comment":"Put the given ItemStack into the boots slot. This does not check if the\n ItemStack is a boots","isClass":false,"isInterface":false,"isEnum":false,"isEnumConstant":false,"isConstructor":false,"isField":false,"isMethod":true,"isOrdinaryClass":false,"signature":"(org.bukkit.inventory.ItemStack)","flatSignature":"(ItemStack)","returnType":{"isPrimitive":true,"simpleName":"void","qualifiedName":"void","dimension":"","elementType":{}},"isAbstract":true,"isDefault":false,"isStatic":false,"parameters":[{"name":"boots","type":{"isPrimitive":false,"simpleName":"ItemStack","qualifiedName":"org.bukkit.inventory.ItemStack","dimension":"","elementType":{}}}],"typeParameters":[]},{"name":"getItemInMainHand","comment":"Gets a copy of the item the player is currently holding\n in their main hand.","isClass":false,"isInterface":false,"isEnum":false,"isEnumConstant":false,"isConstructor":false,"isField":false,"isMethod":true,"isOrdinaryClass":false,"signature":"()","flatSignature":"()","returnType":{"isPrimitive":false,"simpleName":"ItemStack","qualifiedName":"org.bukkit.inventory.ItemStack","dimension":"","elementType":{}},"isAbstract":true,"isDefault":false,"isStatic":false,"parameters":[],"typeParameters":[]},{"name":"setItemInMainHand","comment":"Sets the item the player is holding in their main hand.","isClass":false,"isInterface":false,"isEnum":false,"isEnumConstant":false,"isConstructor":false,"isField":false,"isMethod":true,"isOrdinaryClass":false,"signature":"(org.bukkit.inventory.ItemStack)","flatSignature":"(ItemStack)","returnType":{"isPrimitive":true,"simpleName":"void","qualifiedName":"void","dimension":"","elementType":{}},"isAbstract":true,"isDefault":false,"isStatic":false,"parameters":[{"name":"item","type":{"isPrimitive":false,"simpleName":"ItemStack","qualifiedName":"org.bukkit.inventory.ItemStack","dimension":"","elementType":{}}}],"typeParameters":[]},{"name":"getItemInOffHand","comment":"Gets a copy of the item the player is currently holding\n in their off hand.","isClass":false,"isInterface":false,"isEnum":false,"isEnumConstant":false,"isConstructor":false,"isField":false,"isMethod":true,"isOrdinaryClass":false,"signature":"()","flatSignature":"()","returnType":{"isPrimitive":false,"simpleName":"ItemStack","qualifiedName":"org.bukkit.inventory.ItemStack","dimension":"","elementType":{}},"isAbstract":true,"isDefault":false,"isStatic":false,"parameters":[],"typeParameters":[]},{"name":"setItemInOffHand","comment":"Sets the item the player is holding in their off hand.","isClass":false,"isInterface":false,"isEnum":false,"isEnumConstant":false,"isConstructor":false,"isField":false,"isMethod":true,"isOrdinaryClass":false,"signature":"(org.bukkit.inventory.ItemStack)","flatSignature":"(ItemStack)","returnType":{"isPrimitive":true,"simpleName":"void","qualifiedName":"void","dimension":"","elementType":{}},"isAbstract":true,"isDefault":false,"isStatic":false,"parameters":[{"name":"item","type":{"isPrimitive":false,"simpleName":"ItemStack","qualifiedName":"org.bukkit.inventory.ItemStack","dimension":"","elementType":{}}}],"typeParameters":[]},{"name":"getItemInHand","comment":"Gets a copy of the item the player is currently holding","isClass":false,"isInterface":false,"isEnum":false,"isEnumConstant":false,"isConstructor":false,"isField":false,"isMethod":true,"isOrdinaryClass":false,"signature":"()","flatSignature":"()","returnType":{"isPrimitive":false,"simpleName":"ItemStack","qualifiedName":"org.bukkit.inventory.ItemStack","dimension":"","elementType":{}},"isAbstract":true,"isDefault":false,"isStatic":false,"parameters":[],"typeParameters":[]},{"name":"setItemInHand","comment":"Sets the item the player is holding","isClass":false,"isInterface":false,"isEnum":false,"isEnumConstant":false,"isConstructor":false,"isField":false,"isMethod":true,"isOrdinaryClass":false,"signature":"(org.bukkit.inventory.ItemStack)","flatSignature":"(ItemStack)","returnType":{"isPrimitive":true,"simpleName":"void","qualifiedName":"void","dimension":"","elementType":{}},"isAbstract":true,"isDefault":false,"isStatic":false,"parameters":[{"name":"stack","type":{"isPrimitive":false,"simpleName":"ItemStack","qualifiedName":"org.bukkit.inventory.ItemStack","dimension":"","elementType":{}}}],"typeParameters":[]},{"name":"getHeldItemSlot","comment":"Get the slot number of the currently held item","isClass":false,"isInterface":false,"isEnum":false,"isEnumConstant":false,"isConstructor":false,"isField":false,"isMethod":true,"isOrdinaryClass":false,"signature":"()","flatSignature":"()","returnType":{"isPrimitive":true,"simpleName":"int","qualifiedName":"int","dimension":"","elementType":{}},"isAbstract":true,"isDefault":false,"isStatic":false,"parameters":[],"typeParameters":[]},{"name":"setHeldItemSlot","comment":"Set the slot number of the currently held item.\n \u003cp\u003e\n This validates whether the slot is between 0 and 8 inclusive.","isClass":false,"isInterface":false,"isEnum":false,"isEnumConstant":false,"isConstructor":false,"isField":false,"isMethod":true,"isOrdinaryClass":false,"signature":"(int)","flatSignature":"(int)","returnType":{"isPrimitive":true,"simpleName":"void","qualifiedName":"void","dimension":"","elementType":{}},"isAbstract":true,"isDefault":false,"isStatic":false,"parameters":[{"name":"slot","type":{"isPrimitive":true,"simpleName":"int","qualifiedName":"int","dimension":"","elementType":{}}}],"typeParameters":[]},{"name":"getHolder","comment":"","isClass":false,"isInterface":false,"isEnum":false,"isEnumConstant":false,"isConstructor":false,"isField":false,"isMethod":true,"isOrdinaryClass":false,"signature":"()","flatSignature":"()","returnType":{"isPrimitive":false,"simpleName":"HumanEntity","qualifiedName":"org.bukkit.entity.HumanEntity","dimension":"","elementType":{}},"isAbstract":true,"isDefault":false,"isStatic":false,"parameters":[],"typeParameters":[]}],"typeParameters":[],"enumConstants":[]}