{"name":"BlockPhysicsEvent","comment":"Thrown when a block physics check is called.\n \u003cbr\u003e\n This event is a high frequency event, it may be called thousands of times per\n a second on a busy server. Plugins are advised to listen to the event with\n caution and only perform lightweight checks when using it.\n \u003cbr\u003e\n In addition to this, cancelling the event is liable to leave the world in an\n inconsistent state. For example if you use the event to leave a block\n floating in mid air when that block has a requirement to be attached to\n something, there is no guarantee that the floating block will persist across\n server restarts or map upgrades.\n \u003cbr\u003e\n Plugins should also note that where possible this event may only called for\n the \"root\" block of physics updates in order to limit event spam. Physics\n updates that cause other blocks to change their state may not result in an\n event for each of those blocks (usually adjacent). If you are concerned about\n monitoring these changes then you should check adjacent blocks yourself.","isClass":true,"isInterface":false,"isEnum":false,"isEnumConstant":false,"isConstructor":false,"isField":false,"isMethod":false,"isOrdinaryClass":true,"isPrimitive":false,"simpleName":"BlockPhysicsEvent","qualifiedName":"org.bukkit.event.block.BlockPhysicsEvent","dimension":"","elementType":{},"package":"org.bukkit.event.block","superclass":"org.bukkit.event.block.BlockEvent","interfaces":["org.bukkit.event.Cancellable"],"isAbstract":false,"isStatic":false,"innerClasses":[],"isInnerClass":false,"constructors":[{"name":"BlockPhysicsEvent","comment":"","isClass":false,"isInterface":false,"isEnum":false,"isEnumConstant":false,"isConstructor":true,"isField":false,"isMethod":false,"isOrdinaryClass":false,"signature":"(org.bukkit.block.Block, org.bukkit.block.data.BlockData)","flatSignature":"(Block, BlockData)","parameters":[{"name":"block","type":{"isPrimitive":false,"simpleName":"Block","qualifiedName":"org.bukkit.block.Block","dimension":"","elementType":{}}},{"name":"changed","type":{"isPrimitive":false,"simpleName":"BlockData","qualifiedName":"org.bukkit.block.data.BlockData","dimension":"","elementType":{}}}],"typeParameters":[]}],"fields":[],"methods":[{"name":"getChangedType","comment":"Gets the type of block that changed, causing this event","isClass":false,"isInterface":false,"isEnum":false,"isEnumConstant":false,"isConstructor":false,"isField":false,"isMethod":true,"isOrdinaryClass":false,"signature":"()","flatSignature":"()","returnType":{"isPrimitive":false,"simpleName":"Material","qualifiedName":"org.bukkit.Material","dimension":"","elementType":{}},"isAbstract":false,"isDefault":false,"isStatic":false,"parameters":[],"typeParameters":[]},{"name":"isCancelled","comment":"","isClass":false,"isInterface":false,"isEnum":false,"isEnumConstant":false,"isConstructor":false,"isField":false,"isMethod":true,"isOrdinaryClass":false,"signature":"()","flatSignature":"()","returnType":{"isPrimitive":true,"simpleName":"boolean","qualifiedName":"boolean","dimension":"","elementType":{}},"isAbstract":false,"isDefault":false,"isStatic":false,"parameters":[],"typeParameters":[]},{"name":"setCancelled","comment":"","isClass":false,"isInterface":false,"isEnum":false,"isEnumConstant":false,"isConstructor":false,"isField":false,"isMethod":true,"isOrdinaryClass":false,"signature":"(boolean)","flatSignature":"(boolean)","returnType":{"isPrimitive":true,"simpleName":"void","qualifiedName":"void","dimension":"","elementType":{}},"isAbstract":false,"isDefault":false,"isStatic":false,"parameters":[{"name":"cancel","type":{"isPrimitive":true,"simpleName":"boolean","qualifiedName":"boolean","dimension":"","elementType":{}}}],"typeParameters":[]},{"name":"getHandlers","comment":"","isClass":false,"isInterface":false,"isEnum":false,"isEnumConstant":false,"isConstructor":false,"isField":false,"isMethod":true,"isOrdinaryClass":false,"signature":"()","flatSignature":"()","returnType":{"isPrimitive":false,"simpleName":"HandlerList","qualifiedName":"org.bukkit.event.HandlerList","dimension":"","elementType":{}},"isAbstract":false,"isDefault":false,"isStatic":false,"parameters":[],"typeParameters":[]},{"name":"getHandlerList","comment":"","isClass":false,"isInterface":false,"isEnum":false,"isEnumConstant":false,"isConstructor":false,"isField":false,"isMethod":true,"isOrdinaryClass":false,"signature":"()","flatSignature":"()","returnType":{"isPrimitive":false,"simpleName":"HandlerList","qualifiedName":"org.bukkit.event.HandlerList","dimension":"","elementType":{}},"isAbstract":false,"isDefault":false,"isStatic":true,"parameters":[],"typeParameters":[]}],"typeParameters":[],"enumConstants":[]}