{"name":"Monster","isClass":false,"isInterface":true,"isEnum":false,"isEnumConstant":false,"isConstructor":false,"isField":false,"isMethod":false,"isOrdinaryClass":false,"isPrimitive":false,"simpleName":"Monster","qualifiedName":"org.bukkit.entity.Monster","dimension":"","elementType":{},"package":"org.bukkit.entity","interfaces":["org.bukkit.entity.Creature"],"isAbstract":true,"isStatic":false,"innerClasses":[],"isInnerClass":false,"constructors":[],"fields":[],"methods":[],"typeParameters":[],"subInterfaces":["org.bukkit.entity.Vex","org.bukkit.entity.Guardian","org.bukkit.entity.Zombie","org.bukkit.entity.Spider","org.bukkit.entity.Illager","org.bukkit.entity.Enderman","org.bukkit.entity.Blaze","org.bukkit.entity.Giant","org.bukkit.entity.Wither","org.bukkit.entity.Skeleton","org.bukkit.entity.Witch","org.bukkit.entity.Creeper","org.bukkit.entity.Endermite","org.bukkit.entity.Silverfish"],"enumConstants":[]}