{"name":"Dropper","comment":"Represents a captured state of a dropper.","isClass":false,"isInterface":true,"isEnum":false,"isEnumConstant":false,"isConstructor":false,"isField":false,"isMethod":false,"isOrdinaryClass":false,"isPrimitive":false,"simpleName":"Dropper","qualifiedName":"org.bukkit.block.Dropper","dimension":"","elementType":{},"package":"org.bukkit.block","interfaces":["org.bukkit.block.Container","org.bukkit.Nameable","org.bukkit.loot.Lootable"],"isAbstract":true,"isStatic":false,"innerClasses":[],"isInnerClass":false,"constructors":[],"fields":[],"methods":[{"name":"drop","comment":"Tries to drop a randomly selected item from the dropper\u0027s inventory,\n following the normal behavior of a dropper.\n \u003cp\u003e\n Normal behavior of a dropper is as follows:\n \u003cp\u003e\n If the block that the dropper is facing is an InventoryHolder,\n the randomly selected ItemStack is placed within that \n Inventory in the first slot that\u0027s available, starting with 0 and\n counting up.  If the inventory is full, nothing happens.\n \u003cp\u003e\n If the block that the dropper is facing is not an InventoryHolder,\n the randomly selected ItemStack is dropped on\n the ground in the form of an {@link org.bukkit.entity.Item Item}.\n \u003cp\u003e\n If the block represented by this state is no longer a dropper, this will\n do nothing.","isClass":false,"isInterface":false,"isEnum":false,"isEnumConstant":false,"isConstructor":false,"isField":false,"isMethod":true,"isOrdinaryClass":false,"signature":"()","flatSignature":"()","returnType":{"isPrimitive":true,"simpleName":"void","qualifiedName":"void","dimension":"","elementType":{}},"isAbstract":true,"isDefault":false,"isStatic":false,"parameters":[],"typeParameters":[]}],"typeParameters":[],"enumConstants":[]}