{"name":"InventoryCreativeEvent","isClass":true,"isInterface":false,"isEnum":false,"isEnumConstant":false,"isConstructor":false,"isField":false,"isMethod":false,"isOrdinaryClass":true,"isPrimitive":false,"simpleName":"InventoryCreativeEvent","qualifiedName":"org.bukkit.event.inventory.InventoryCreativeEvent","dimension":"","elementType":{},"package":"org.bukkit.event.inventory","superclass":"org.bukkit.event.inventory.InventoryClickEvent","interfaces":[],"isAbstract":false,"isStatic":false,"innerClasses":[],"isInnerClass":false,"constructors":[{"name":"InventoryCreativeEvent","isClass":false,"isInterface":false,"isEnum":false,"isEnumConstant":false,"isConstructor":true,"isField":false,"isMethod":false,"isOrdinaryClass":false,"signature":"(org.bukkit.inventory.InventoryView, org.bukkit.event.inventory.InventoryType.SlotType, int, org.bukkit.inventory.ItemStack)","flatSignature":"(InventoryView, InventoryType.SlotType, int, ItemStack)","parameters":[{"name":"what","type":{"isPrimitive":false,"simpleName":"InventoryView","qualifiedName":"org.bukkit.inventory.InventoryView","dimension":"","elementType":{}}},{"name":"type","type":{"isPrimitive":false,"simpleName":"SlotType","qualifiedName":"org.bukkit.event.inventory.InventoryType.SlotType","dimension":"","elementType":{}}},{"name":"slot","type":{"isPrimitive":true,"simpleName":"int","qualifiedName":"int","dimension":"","elementType":{}}},{"name":"newItem","type":{"isPrimitive":false,"simpleName":"ItemStack","qualifiedName":"org.bukkit.inventory.ItemStack","dimension":"","elementType":{}}}],"typeParameters":[]}],"fields":[],"methods":[{"name":"getCursor","isClass":false,"isInterface":false,"isEnum":false,"isEnumConstant":false,"isConstructor":false,"isField":false,"isMethod":true,"isOrdinaryClass":false,"signature":"()","flatSignature":"()","returnType":{"isPrimitive":false,"simpleName":"ItemStack","qualifiedName":"org.bukkit.inventory.ItemStack","dimension":"","elementType":{}},"isAbstract":false,"isDefault":false,"isStatic":false,"parameters":[],"typeParameters":[]},{"name":"setCursor","isClass":false,"isInterface":false,"isEnum":false,"isEnumConstant":false,"isConstructor":false,"isField":false,"isMethod":true,"isOrdinaryClass":false,"signature":"(org.bukkit.inventory.ItemStack)","flatSignature":"(ItemStack)","returnType":{"isPrimitive":true,"simpleName":"void","qualifiedName":"void","dimension":"","elementType":{}},"isAbstract":false,"isDefault":false,"isStatic":false,"parameters":[{"name":"item","type":{"isPrimitive":false,"simpleName":"ItemStack","qualifiedName":"org.bukkit.inventory.ItemStack","dimension":"","elementType":{}}}],"typeParameters":[]}],"typeParameters":[],"enumConstants":[]}