{"name":"PerlinNoiseGenerator","comment":"Generates noise using the \"classic\" perlin generator","isClass":true,"isInterface":false,"isEnum":false,"isEnumConstant":false,"isConstructor":false,"isField":false,"isMethod":false,"isOrdinaryClass":true,"isPrimitive":false,"simpleName":"PerlinNoiseGenerator","qualifiedName":"org.bukkit.util.noise.PerlinNoiseGenerator","dimension":"","elementType":{},"package":"org.bukkit.util.noise","superclass":"org.bukkit.util.noise.NoiseGenerator","interfaces":[],"isAbstract":false,"isStatic":false,"innerClasses":[],"isInnerClass":false,"constructors":[{"name":"PerlinNoiseGenerator","comment":"Creates a seeded perlin noise generator for the given world","isClass":false,"isInterface":false,"isEnum":false,"isEnumConstant":false,"isConstructor":true,"isField":false,"isMethod":false,"isOrdinaryClass":false,"signature":"(org.bukkit.World)","flatSignature":"(World)","parameters":[{"name":"world","type":{"isPrimitive":false,"simpleName":"World","qualifiedName":"org.bukkit.World","dimension":"","elementType":{}}}],"typeParameters":[]},{"name":"PerlinNoiseGenerator","comment":"Creates a seeded perlin noise generator for the given seed","isClass":false,"isInterface":false,"isEnum":false,"isEnumConstant":false,"isConstructor":true,"isField":false,"isMethod":false,"isOrdinaryClass":false,"signature":"(long)","flatSignature":"(long)","parameters":[{"name":"seed","type":{"isPrimitive":true,"simpleName":"long","qualifiedName":"long","dimension":"","elementType":{}}}],"typeParameters":[]},{"name":"PerlinNoiseGenerator","comment":"Creates a seeded perlin noise generator with the given Random","isClass":false,"isInterface":false,"isEnum":false,"isEnumConstant":false,"isConstructor":true,"isField":false,"isMethod":false,"isOrdinaryClass":false,"signature":"(java.util.Random)","flatSignature":"(Random)","parameters":[{"name":"rand","type":{"isPrimitive":false,"simpleName":"Random","qualifiedName":"java.util.Random","dimension":"","elementType":{}}}],"typeParameters":[]}],"fields":[],"methods":[{"name":"getNoise","comment":"Computes and returns the 1D unseeded perlin noise for the given\n coordinates in 1D space","isClass":false,"isInterface":false,"isEnum":false,"isEnumConstant":false,"isConstructor":false,"isField":false,"isMethod":true,"isOrdinaryClass":false,"signature":"(double)","flatSignature":"(double)","returnType":{"isPrimitive":true,"simpleName":"double","qualifiedName":"double","dimension":"","elementType":{}},"isAbstract":false,"isDefault":false,"isStatic":true,"parameters":[{"name":"x","type":{"isPrimitive":true,"simpleName":"double","qualifiedName":"double","dimension":"","elementType":{}}}],"typeParameters":[]},{"name":"getNoise","comment":"Computes and returns the 2D unseeded perlin noise for the given\n coordinates in 2D space","isClass":false,"isInterface":false,"isEnum":false,"isEnumConstant":false,"isConstructor":false,"isField":false,"isMethod":true,"isOrdinaryClass":false,"signature":"(double, double)","flatSignature":"(double, double)","returnType":{"isPrimitive":true,"simpleName":"double","qualifiedName":"double","dimension":"","elementType":{}},"isAbstract":false,"isDefault":false,"isStatic":true,"parameters":[{"name":"x","type":{"isPrimitive":true,"simpleName":"double","qualifiedName":"double","dimension":"","elementType":{}}},{"name":"y","type":{"isPrimitive":true,"simpleName":"double","qualifiedName":"double","dimension":"","elementType":{}}}],"typeParameters":[]},{"name":"getNoise","comment":"Computes and returns the 3D unseeded perlin noise for the given\n coordinates in 3D space","isClass":false,"isInterface":false,"isEnum":false,"isEnumConstant":false,"isConstructor":false,"isField":false,"isMethod":true,"isOrdinaryClass":false,"signature":"(double, double, double)","flatSignature":"(double, double, double)","returnType":{"isPrimitive":true,"simpleName":"double","qualifiedName":"double","dimension":"","elementType":{}},"isAbstract":false,"isDefault":false,"isStatic":true,"parameters":[{"name":"x","type":{"isPrimitive":true,"simpleName":"double","qualifiedName":"double","dimension":"","elementType":{}}},{"name":"y","type":{"isPrimitive":true,"simpleName":"double","qualifiedName":"double","dimension":"","elementType":{}}},{"name":"z","type":{"isPrimitive":true,"simpleName":"double","qualifiedName":"double","dimension":"","elementType":{}}}],"typeParameters":[]},{"name":"getInstance","comment":"Gets the singleton unseeded instance of this generator","isClass":false,"isInterface":false,"isEnum":false,"isEnumConstant":false,"isConstructor":false,"isField":false,"isMethod":true,"isOrdinaryClass":false,"signature":"()","flatSignature":"()","returnType":{"isPrimitive":false,"simpleName":"PerlinNoiseGenerator","qualifiedName":"org.bukkit.util.noise.PerlinNoiseGenerator","dimension":"","elementType":{}},"isAbstract":false,"isDefault":false,"isStatic":true,"parameters":[],"typeParameters":[]},{"name":"noise","comment":"","isClass":false,"isInterface":false,"isEnum":false,"isEnumConstant":false,"isConstructor":false,"isField":false,"isMethod":true,"isOrdinaryClass":false,"signature":"(double, double, double)","flatSignature":"(double, double, double)","returnType":{"isPrimitive":true,"simpleName":"double","qualifiedName":"double","dimension":"","elementType":{}},"isAbstract":false,"isDefault":false,"isStatic":false,"parameters":[{"name":"x","type":{"isPrimitive":true,"simpleName":"double","qualifiedName":"double","dimension":"","elementType":{}}},{"name":"y","type":{"isPrimitive":true,"simpleName":"double","qualifiedName":"double","dimension":"","elementType":{}}},{"name":"z","type":{"isPrimitive":true,"simpleName":"double","qualifiedName":"double","dimension":"","elementType":{}}}],"typeParameters":[]},{"name":"getNoise","comment":"Generates noise for the 1D coordinates using the specified number of\n octaves and parameters","isClass":false,"isInterface":false,"isEnum":false,"isEnumConstant":false,"isConstructor":false,"isField":false,"isMethod":true,"isOrdinaryClass":false,"signature":"(double, int, double, double)","flatSignature":"(double, int, double, double)","returnType":{"isPrimitive":true,"simpleName":"double","qualifiedName":"double","dimension":"","elementType":{}},"isAbstract":false,"isDefault":false,"isStatic":true,"parameters":[{"name":"x","type":{"isPrimitive":true,"simpleName":"double","qualifiedName":"double","dimension":"","elementType":{}}},{"name":"octaves","type":{"isPrimitive":true,"simpleName":"int","qualifiedName":"int","dimension":"","elementType":{}}},{"name":"frequency","type":{"isPrimitive":true,"simpleName":"double","qualifiedName":"double","dimension":"","elementType":{}}},{"name":"amplitude","type":{"isPrimitive":true,"simpleName":"double","qualifiedName":"double","dimension":"","elementType":{}}}],"typeParameters":[]},{"name":"getNoise","comment":"Generates noise for the 2D coordinates using the specified number of\n octaves and parameters","isClass":false,"isInterface":false,"isEnum":false,"isEnumConstant":false,"isConstructor":false,"isField":false,"isMethod":true,"isOrdinaryClass":false,"signature":"(double, double, int, double, double)","flatSignature":"(double, double, int, double, double)","returnType":{"isPrimitive":true,"simpleName":"double","qualifiedName":"double","dimension":"","elementType":{}},"isAbstract":false,"isDefault":false,"isStatic":true,"parameters":[{"name":"x","type":{"isPrimitive":true,"simpleName":"double","qualifiedName":"double","dimension":"","elementType":{}}},{"name":"y","type":{"isPrimitive":true,"simpleName":"double","qualifiedName":"double","dimension":"","elementType":{}}},{"name":"octaves","type":{"isPrimitive":true,"simpleName":"int","qualifiedName":"int","dimension":"","elementType":{}}},{"name":"frequency","type":{"isPrimitive":true,"simpleName":"double","qualifiedName":"double","dimension":"","elementType":{}}},{"name":"amplitude","type":{"isPrimitive":true,"simpleName":"double","qualifiedName":"double","dimension":"","elementType":{}}}],"typeParameters":[]},{"name":"getNoise","comment":"Generates noise for the 3D coordinates using the specified number of\n octaves and parameters","isClass":false,"isInterface":false,"isEnum":false,"isEnumConstant":false,"isConstructor":false,"isField":false,"isMethod":true,"isOrdinaryClass":false,"signature":"(double, double, double, int, double, double)","flatSignature":"(double, double, double, int, double, double)","returnType":{"isPrimitive":true,"simpleName":"double","qualifiedName":"double","dimension":"","elementType":{}},"isAbstract":false,"isDefault":false,"isStatic":true,"parameters":[{"name":"x","type":{"isPrimitive":true,"simpleName":"double","qualifiedName":"double","dimension":"","elementType":{}}},{"name":"y","type":{"isPrimitive":true,"simpleName":"double","qualifiedName":"double","dimension":"","elementType":{}}},{"name":"z","type":{"isPrimitive":true,"simpleName":"double","qualifiedName":"double","dimension":"","elementType":{}}},{"name":"octaves","type":{"isPrimitive":true,"simpleName":"int","qualifiedName":"int","dimension":"","elementType":{}}},{"name":"frequency","type":{"isPrimitive":true,"simpleName":"double","qualifiedName":"double","dimension":"","elementType":{}}},{"name":"amplitude","type":{"isPrimitive":true,"simpleName":"double","qualifiedName":"double","dimension":"","elementType":{}}}],"typeParameters":[]}],"typeParameters":[],"subClasses":["org.bukkit.util.noise.SimplexNoiseGenerator"],"enumConstants":[]}