{"name":"PotionSplashEvent","isClass":true,"isInterface":false,"isEnum":false,"isEnumConstant":false,"isConstructor":false,"isField":false,"isMethod":false,"isOrdinaryClass":true,"isPrimitive":false,"simpleName":"PotionSplashEvent","qualifiedName":"org.bukkit.event.entity.PotionSplashEvent","dimension":"","elementType":{},"package":"org.bukkit.event.entity","superclass":"org.bukkit.event.entity.ProjectileHitEvent","interfaces":["org.bukkit.event.Cancellable"],"isAbstract":false,"isStatic":false,"innerClasses":[],"isInnerClass":false,"constructors":[{"name":"PotionSplashEvent","isClass":false,"isInterface":false,"isEnum":false,"isEnumConstant":false,"isConstructor":true,"isField":false,"isMethod":false,"isOrdinaryClass":false,"signature":"(org.bukkit.entity.ThrownPotion, java.util.Map\u003corg.bukkit.entity.LivingEntity, java.lang.Double\u003e)","parameters":[{"name":"potion","type":{"isPrimitive":false,"simpleName":"ThrownPotion","qualifiedName":"org.bukkit.entity.ThrownPotion","dimension":"","elementType":{}}},{"name":"affectedEntities","type":{"isPrimitive":false,"simpleName":"Map","qualifiedName":"java.util.Map","dimension":"","elementType":{}}}],"typeParameters":[]}],"fields":[],"methods":[{"name":"getEntity","isClass":false,"isInterface":false,"isEnum":false,"isEnumConstant":false,"isConstructor":false,"isField":false,"isMethod":true,"isOrdinaryClass":false,"signature":"()","returnType":{"isPrimitive":false,"simpleName":"ThrownPotion","qualifiedName":"org.bukkit.entity.ThrownPotion","dimension":"","elementType":{}},"isAbstract":false,"isDefault":false,"isStatic":false,"parameters":[],"typeParameters":[]},{"name":"getPotion","isClass":false,"isInterface":false,"isEnum":false,"isEnumConstant":false,"isConstructor":false,"isField":false,"isMethod":true,"isOrdinaryClass":false,"signature":"()","returnType":{"isPrimitive":false,"simpleName":"ThrownPotion","qualifiedName":"org.bukkit.entity.ThrownPotion","dimension":"","elementType":{}},"isAbstract":false,"isDefault":false,"isStatic":false,"parameters":[],"typeParameters":[]},{"name":"getAffectedEntities","isClass":false,"isInterface":false,"isEnum":false,"isEnumConstant":false,"isConstructor":false,"isField":false,"isMethod":true,"isOrdinaryClass":false,"signature":"()","returnType":{"isPrimitive":false,"simpleName":"Collection","qualifiedName":"java.util.Collection","dimension":"","elementType":{}},"isAbstract":false,"isDefault":false,"isStatic":false,"parameters":[],"typeParameters":[]},{"name":"getIntensity","isClass":false,"isInterface":false,"isEnum":false,"isEnumConstant":false,"isConstructor":false,"isField":false,"isMethod":true,"isOrdinaryClass":false,"signature":"(org.bukkit.entity.LivingEntity)","returnType":{"isPrimitive":true,"simpleName":"double","qualifiedName":"double","dimension":"","elementType":{}},"isAbstract":false,"isDefault":false,"isStatic":false,"parameters":[{"name":"entity","type":{"isPrimitive":false,"simpleName":"LivingEntity","qualifiedName":"org.bukkit.entity.LivingEntity","dimension":"","elementType":{}}}],"typeParameters":[]},{"name":"setIntensity","isClass":false,"isInterface":false,"isEnum":false,"isEnumConstant":false,"isConstructor":false,"isField":false,"isMethod":true,"isOrdinaryClass":false,"signature":"(org.bukkit.entity.LivingEntity, double)","returnType":{"isPrimitive":true,"simpleName":"void","qualifiedName":"void","dimension":"","elementType":{}},"isAbstract":false,"isDefault":false,"isStatic":false,"parameters":[{"name":"entity","type":{"isPrimitive":false,"simpleName":"LivingEntity","qualifiedName":"org.bukkit.entity.LivingEntity","dimension":"","elementType":{}}},{"name":"intensity","type":{"isPrimitive":true,"simpleName":"double","qualifiedName":"double","dimension":"","elementType":{}}}],"typeParameters":[]},{"name":"isCancelled","isClass":false,"isInterface":false,"isEnum":false,"isEnumConstant":false,"isConstructor":false,"isField":false,"isMethod":true,"isOrdinaryClass":false,"signature":"()","returnType":{"isPrimitive":true,"simpleName":"boolean","qualifiedName":"boolean","dimension":"","elementType":{}},"isAbstract":false,"isDefault":false,"isStatic":false,"parameters":[],"typeParameters":[]},{"name":"setCancelled","isClass":false,"isInterface":false,"isEnum":false,"isEnumConstant":false,"isConstructor":false,"isField":false,"isMethod":true,"isOrdinaryClass":false,"signature":"(boolean)","returnType":{"isPrimitive":true,"simpleName":"void","qualifiedName":"void","dimension":"","elementType":{}},"isAbstract":false,"isDefault":false,"isStatic":false,"parameters":[{"name":"cancel","type":{"isPrimitive":true,"simpleName":"boolean","qualifiedName":"boolean","dimension":"","elementType":{}}}],"typeParameters":[]},{"name":"getHandlers","isClass":false,"isInterface":false,"isEnum":false,"isEnumConstant":false,"isConstructor":false,"isField":false,"isMethod":true,"isOrdinaryClass":false,"signature":"()","returnType":{"isPrimitive":false,"simpleName":"HandlerList","qualifiedName":"org.bukkit.event.HandlerList","dimension":"","elementType":{}},"isAbstract":false,"isDefault":false,"isStatic":false,"parameters":[],"typeParameters":[]},{"name":"getHandlerList","isClass":false,"isInterface":false,"isEnum":false,"isEnumConstant":false,"isConstructor":false,"isField":false,"isMethod":true,"isOrdinaryClass":false,"signature":"()","returnType":{"isPrimitive":false,"simpleName":"HandlerList","qualifiedName":"org.bukkit.event.HandlerList","dimension":"","elementType":{}},"isAbstract":false,"isDefault":false,"isStatic":true,"parameters":[],"typeParameters":[]}],"typeParameters":[],"enumConstants":[]}